LICENSE
MANIFEST.in
README.rst
requirements.txt
setup.py
unitconv/__init__.py
unitconv.egg-info/PKG-INFO
unitconv.egg-info/SOURCES.txt
unitconv.egg-info/dependency_links.txt
unitconv.egg-info/entry_points.txt
unitconv.egg-info/requires.txt
unitconv.egg-info/top_level.txt