Metadata-Version: 2.1
Name: unitconv
Version: 1
Summary: A units converter that understands a lot of written queries and produce a nice human response
Home-page: https://github.com/facundobatista/unitconv
Author: Facundo Batista
Author-email: facundo@taniquetil.com.ar
License: UNKNOWN
Platform: UNKNOWN
Classifier: Environment :: Console
Classifier: License :: OSI Approved :: Apache Software License
Classifier: Operating System :: OS Independent
Classifier: Programming Language :: Python :: 3
Requires-Python: >=3
